{"Title":"The Butterfly Effect","Year":"2004","Rated":"R","Released":"23 Jan 2004","Runtime":"113 min","Genre":"Sci-Fi, Thriller","Director":"Eric Bress, J. Mackye Gruber","Writer":"J. Mackye Gruber, Eric Bress","Actors":"Ashton Kutcher, Melora Walters, Amy Smart, Elden Henson","Plot":"A young man blocks out harmful memories of significant events of his life. As he grows up, he finds a way to remember these lost memories and a supernatural way to alter his life.","Language":"English","Country":"USA, Canada","Awards":"1 win & 4 nominations.","Poster":"http://ia.media-imdb.com/images/M/MV5BMTI1ODkxNzg2N15BMl5BanBnXkFtZTYwMzQ2MTg2._V1_SX300.jpg","Metascore":"30","imdbRating":"7.7","imdbVotes":"262,426","imdbID":"tt0289879","Type":"movie","Response":"True"}